metcalculator
