Metadata-Version: 1.0
Name: metcalculator
Version: 1.4.5
Summary: Calculate various meteorological parameters
Home-page: www.metpod.co.uk
Author: Mark Baker
Author-email: mark2182@mac.com
License: MIT
Platform: UNKNOWN
